{
  "name": "Fixed Deposit Calculator",
  "desc": "Term Deposit Calculator. Free online calculator with formula, examples and step-by-step guide.",
  "description": "Calculate fixed deposit returns.",
  "seo_title": "Term Deposit Calculator – Free Online Tool",
  "seo_description": "Use our free term deposit calculator to quickly estimate interest, total based on capital, tasa_anual, plazo_meses. Not registration needed.",
  "inputs": {
    "capital": "Principal",
    "tasa_anual": "Annual rate (%)",
    "plazo_meses": "Term (months)"
  },
  "outputs": {
    "intereses": "Interest",
    "total": "Total"
  },
  "example_label": "Calculatete 10,000 EUR at 2.5% for 12 months.",
  "range_hints": {
    "capital": "â‚¬1,000 - â‚¬500,000 deposit amounts",
    "tasa_anual": "1-6% term deposit rates",
    "plazo_meses": "3-60 months typical terms"
  },
  "result_context": "The interes is of {intereses} is earned over the term. the total of {total} is returned at maturity.",
  "formula_display": "Interest = main × Rate × (Months ÷ 12)",
  "steps": [
    "{'step': 1, 'description': 'Convert annual rate to decimal', 'calculation': '3.5% ÷ 100 = 0.035'}",
    "{'step': 2, 'description': 'Calculatete time factor in years', 'calculation': '18 months ÷ 12 = 1.5 years'}",
    "{'step': 3, 'description': 'Calculatete simple interest', 'calculation': '€20,000 × 0.035 × 1.5 = €1,050'}",
    "{'step': 4, 'description': 'Add interest to main', 'calculation': '€20,000 + €1,050 = €21,050'}"
  ],
  "mistakes": [
    "Not checking early withdrawal penalti is before investing",
    "Confusing nominal rate with effective annual rate",
    "Forgetting to compare with inflation for current returns"
  ]
}