{
  "name": "Credit Card Payoff Calculator",
  "description": "Calculate credit card payoff time.",
  "inputs": {
    "balance": "Balance",
    "rate": "Rate %",
    "payment": "Monthly payment"
  },
  "outputs": {
    "months": "Months",
    "total_interest": "Total interest"
  },
  "seo_title": "Credit Card Payoff Calculator – Step-by-Step",
  "seo_description": "Free credit card payoff calculator: calculate months, total_interest from your balance, rate, payment. Instant results, no sign-up required.",
  "example_label": "Calculate: 5,000 EUR debt, 18% APR, 200 EUR/month.",
  "range_hints": {
    "balance": "Varía according to debt",
    "rate": "Típicamente 12-30% for tarjetas",
    "payment": "Debe ser mayor al interest mensual mínimo"
  },
  "result_context": "Time necessary to pagar The debt and total of intereses",
  "formula_display": "Simulación iterativa: Balance_n+1 = Balance_n - (payment - interest)",
  "steps": [
    "Calculate interest mensual (balance × rate/12)",
    "Subtract interest of the payment to Obtain abono a capital",
    "Reducir balance per The abono a capital",
    "Repetir to saldo cero"
  ],
  "mistakes": [
    "Hacer solo payment minimum (nunca se liquida)",
    "No Consider nuevos cargos"
  ],
  "desc": "Free online credit card payoff calculator. Enter balance and rate % to get instant results."
}