{
  "name": "Rendement Locatif",
  "description": "Calculez le rendement locatif brut annuel d'un bien immobilier.",
  "inputs": {
    "annual_rent": "Loyer annuel",
    "property_value": "Valeur du bien"
  },
  "outputs": {
    "yield_pct": "Rendement %"
  },
  "seo_title": "Rendement Locatif – Rapide et Précis",
  "seo_description": "Calculez le rendement locatif brut annuel d'un bien immobilier. Calculateur gratuit, précis et instantané. Outil gratuit avec formule et exemples.",
  "example_label": "Calculating gross rental yield for property worth $320,generating $18,annual rent.",
  "range_hints": {
    "annual_rent": "$5,000 - $200,000+ annual rental income",
    "property_value": "$50,000 - $5,000,000+ property values"
  },
  "result_context": "The yield_pct of {yield_pct}% is the gross rental yield before expenses and vacancies.",
  "formula_display": "Rental Yield% = (Annual Rent ÷ Property Value) × 100",
  "steps": [
    "{'step': 1, 'description': 'Divide annual rent by property value', 'calculetion': '$18,÷ $320,000 = 0.05625'}",
    "{'step': 2, 'description': 'Convert to percentage', 'calculetion': '0.05625 × 100 = 5.625%'}"
  ],
  "mistakes": [
    "Using gross yield without accounting for expenses (taxes, maintenance, vacancies)",
    "Not including purchase costs in Total investment calculetion",
    "Comparing yields across markets without considering appreciation potential"
  ]
}