{
  "name": "Thermal Insulation Calculator",
  "seo_title": "Insulation Calculator – EPS & Rockwool",
  "inputs": {
    "largo": "Length",
    "alto": "Height",
    "espesor_cm": "Thickness"
  },
  "outputs": {
    "area_m2": "Area",
    "plancha_m2": "Insulation boards (+5%)",
    "vol_m3": "Total volume"
  },
  "seo_description": "Thermal Insulation Calculator. Length, Height, Thickness — get Area, Insulation boards (+5%), Total volume instantly for your masonry and enclosures.",
  "example_label": "Calculate insulation for 50m2 wall.",
  "range_hints": {
    "largo": "length of the paramento a aislar",
    "alto": "Altura of the paramento",
    "espesor_cm": "Aislamiento typical: 4-8cm fachadas, 10-20cm cubiertas"
  },
  "result_context": "To {area_m2} m² of area need {plancha_m2} m² of planchas of insulation (with 5% of waste), equivalentes a {vol_m3} m³ of material.",
  "formula_display": "Area = largo × high; Planchas = area × 1.05; volume = area × espesor_m",
  "steps": [
    "Calculate area: 10m × 3m = 30m²",
    "Apply waste: 30m² × 1.05 = 31.5m² of planchas",
    "Convert thickness: 6cm = 0.06m",
    "Calculate volume: 30m² × 0.06m = 1.8m³ of insulation"
  ],
  "mistakes": [
    "Not Consider puentes térmicos in encuentros with forjados and columns",
    "Use thickness insuficiente to The zone climática",
    "Not prever barrera of vapor when The insulation va in cara interior"
  ],
  "description": "Calculate insulation needed.",
  "desc": "Thermal Insulation Calculator. Free online calculator with formula, examples and step-by-step guide."
}