{
  "id": "416",
  "slug": "indice-adiposidad-corporal",
  "block": 14,
  "block_slug": "salud",
  "inputs": [
    {
      "id": "hip",
      "type": "number",
      "step": "any",
      "default": 100,
      "unit": "cm",
      "unit_options": [
        "cm",
        "in"
      ],
      "unit_category": "length"
    },
    {
      "id": "height",
      "type": "number",
      "step": "any",
      "default": 175,
      "unit": "cm",
      "unit_options": [
        "cm",
        "ft"
      ],
      "unit_category": "length"
    }
  ],
  "formula": "var hip=parseFloat(inputs.hip)||0;var h=parseFloat(inputs.height)||0;var bai=h>0?((hip/Math.pow(h/100,1.5))-18):0;return{bai:bai.toFixed(2)};",
  "outputs": [
    {
      "id": "bai",
      "unit": "%"
    }
  ],
  "related": [
    "415",
    "400",
    "425",
    "426"
  ],
  "example_inputs": {
    "hip": 175,
    "height": 175
  },
  "comparison_presets": [
    {
      "_label": "Child",
      "hip": 88,
      "height": 88
    },
    {
      "_label": "Teen",
      "hip": 131,
      "height": 131
    },
    {
      "_label": "Adult (F)",
      "hip": 175,
      "height": 175
    },
    {
      "_label": "Adult (M)",
      "hip": 262,
      "height": 262
    },
    {
      "_label": "Elderly",
      "hip": 350,
      "height": 350
    }
  ],
  "units": {
    "hip": "m",
    "height": "m"
  }
}