{
  "id": "411",
  "slug": "frecuencia-cardiaca-max-salud",
  "block": 12,
  "block_slug": "salud",
  "inputs": [
    {
      "id": "edad",
      "type": "number",
      "min": 1,
      "max": 100,
      "step": "any",
      "default": 30,
      "unit": ""
    }
  ],
  "formula": "var age=parseFloat(inputs.edad)||0;if(!age)return{error:true};return{fc_tanaka:+(208-.7*age).toFixed(0),fc_haskell:+(220-age),fc_arena:+(205.8-.685*age).toFixed(0),fc_gulati:+(206-.88*age).toFixed(0)};",
  "outputs": [
    {
      "id": "fc_tanaka",
      "unit": "bpm",
      "highlight": true
    },
    {
      "id": "fc_haskell",
      "unit": "bpm"
    },
    {
      "id": "fc_arena",
      "unit": "bpm"
    },
    {
      "id": "fc_gulati",
      "unit": "bpm"
    }
  ],
  "related": [
    "400",
    "410",
    "401",
    "413"
  ],
  "example_inputs": {
    "edad": 30
  },
  "comparison_presets": [
    {
      "_label": "Child",
      "edad": 15
    },
    {
      "_label": "Teen",
      "edad": 22
    },
    {
      "_label": "Adult (F)",
      "edad": 30
    },
    {
      "_label": "Adult (M)",
      "edad": 45
    },
    {
      "_label": "Elderly",
      "edad": 60
    }
  ],
  "i18n": {
    "es": {
      "name": "Calculadora de Frecuencia Cardíaca Máxima",
      "desc": "Calculadora de Frecuencia Cardíaca Máxima. Edad para calcular tus FC máx. Tanaka, FC máx. Haskell, FC máx. Arena. Basado en la fórmula de salud y.",
      "description": "Calculadora Frecuencia Cardiaca Max Salud",
      "seo_title": "Calculadora Frecuencia Cardiaca Max Salud Online Gratis",
      "seo_description": "Calculadora de Frecuencia Cardíaca Máxima. Edad para calcular tus FC máx. Tanaka, FC máx. Haskell, FC máx. Arena. Basado en la fórmula de salud y.",
      "inputs": {
        "edad": "Edad"
      },
      "outputs": {
        "fc_tanaka": "FC máx. Tanaka",
        "fc_haskell": "FC máx. Haskell",
        "fc_arena": "FC máx. Arena",
        "fc_gulati": "FC máx. Gulati"
      },
      "example_label": "Calcular frecuencia cardíaca máxima para persona de 30 años",
      "range_hints": {
        "edad": "Edad típica: 18-80 "
      },
      "result_context": "Las diferentes fórmulas producen variaciones de 5-10 bpm; Tanaka es más precisa para adultos mayores.",
      "formula_display": "Tanaka: FCmáx = 208 - 0.7 × edad; Haskell: FCmáx = 220 - edad",
      "steps": [
        "Ingresa edad en años",
        "Aplica fórmula Tanaka: 208 - 0.7 × edad",
        "Aplica fórmula Haskell: 220 - edad (tradicional)",
        "Compara con fórmulas Arena y Gulati para mujeres"
      ],
      "mistakes": [
        "Usar solo fórmula 220-edad (desactualizada, sobreestima en mayores)",
        "Entrenar siempre al máximo (debe variar por zona de entrenamiento)",
        "Ignorar médicamentos que afectan frecuencia cardíaca (betabloqueadores)"
      ]
    },
    "en": {
      "name": "Body Fat Percentage Calculator (Marina)",
      "desc": "Max Heart Rate Health Calculator. Free online calculator with formula, examples and step-by-step guide.",
      "description": "Calculate body fat percentage using the Spanish Navy method. Enter measurements for body composition.",
      "seo_title": "Body Fat Marina Calculator — % Body Fat | CalcToWork",
      "seo_description": "Calculate body fat percentage. Free fitness and body composition calculator.",
      "inputs": {
        "edad": "Age"
      },
      "outputs": {
        "fc_tanaka": "Max HR Tanaka",
        "fc_haskell": "Max HR Haskell",
        "fc_arena": "Max HR Arena",
        "fc_gulati": "Max HR Gulati"
      },
      "example_label": "Calculate frequency heart máxima to persona of 30 years",
      "range_hints": {
        "edad": "Edad típica: 18-80"
      },
      "result_context": "The different fórmulas producen variaciones of 5-10 bpm; Tanaka es more precise to adultos mayores.",
      "formula_display": "Tanaka: FCmáx = 208 - 0.7 × edad; Haskell: FCmáx = 220 - edad",
      "steps": [
        "Ingresa edad in years",
        "Aplica formula Tanaka: 208 - 0.7 × edad",
        "Aplica formula Haskell: 220 - edad (tradicional)",
        "Compara with fórmulas Arena and Gulati to mujeres"
      ],
      "mistakes": [
        "Use solo formula 220-edad (desactualizada, sobreestima in mayores)",
        "Entrenar siempre to the maximum (debe variar per zone of training)",
        "Ignorar medicamentos que afectan frequency heart (betabloqueadores)"
      ]
    },
    "fr": {
      "name": "Body Fat Percentage Calculator (Marina)",
      "desc": "Calculez Max HR = 220 - age (classic formula). Exemple: 35-year-old person = Max HR = 185 bpm. Calculateur gratuit et précis, sans inscription.",
      "description": "Calculateur Fc Max Sante",
      "seo_title": "Calculateur Fc Max Sante – Rapide et Précis",
      "seo_description": "Calculez Max HR = 220 - age (classic formula). Exemple: 35-year-old person = Max HR = 185 bpm. Calculateur gratuit et précis, sans inscription.",
      "inputs": {
        "edad": "Âge"
      },
      "outputs": {
        "fc_tanaka": "FC max Tanaka",
        "fc_haskell": "FC max Haskell",
        "fc_arena": "FC max Arena",
        "fc_gulati": "FC max Gulati"
      },
      "example_label": "Calculer fréquence cardíaca máxima pour persona de ans",
      "range_hints": {
        "edad": "Edad typique: 18-80"
      },
      "result_context": "Les différentes fórmulas produisent variaciones de 5-bpm; Tanaka est plus précise pour adultos mayores.",
      "formula_display": "Tanaka: FCmáx = 208 - 0.7 × edad; Haskell: FCmáx = 220 - edad",
      "steps": [
        "Ingresa edad en ans",
        "Aplica formule Tanaka: 208 - 0.7 × edad",
        "Aplica formule Haskell: 220 - edad (tradicional)",
        "Compara avec fórmulas sable et Gulati pour mujeres"
      ],
      "mistakes": [
        "Utiliser seulement formule 220-edad (desactualizada, sobreestima en mayores)",
        "Entrenar toujours au maximum (doit variar par zona de entrenamiento)",
        "Ignorer medicamentos que afectan fréquence cardíaca (betabloqueadores)"
      ]
    },
    "pt": {
      "name": "Body Fat Percentage Calculator (Marina)",
      "desc": "Calcule Max HR = 220 - age (classic formula). Exemplo: 35-year-old person = Max HR = 185 bpm. Calculadora grátis e precisa, sem registo.",
      "description": "Calculadora Frequencia Cardiaca Max Saude",
      "seo_title": "Calculadora Frequencia Cardiaca Max Saude",
      "seo_description": "Calcule Max HR = 220 - age (classic formula). Exemplo: 35-year-old person = Max HR = 185 bpm. Calculadora grátis e precisa, sem registo.",
      "inputs": {
        "edad": "Idade"
      },
      "outputs": {
        "fc_tanaka": "FC máx. Tanaka",
        "fc_haskell": "FC máx. Haskell",
        "fc_arena": "FC máx. Arena",
        "fc_gulati": "FC máx. Gulati"
      },
      "example_label": "Calcular frecuencia cardíaca máxima para persona de 30 anos",
      "range_hints": {
        "edad": "Edad típica: 18-80"
      },
      "result_context": "Las Diferentes fórmulas producen variações de 5-10 bpm; Tanaka é mais precisa para adultos mayores.",
      "formula_display": "Tanaka: FCmáx = 208 - 0.7 × edad; Haskell: FCmáx = 220 - edad",
      "steps": [
        "Ingresa edad em anos",
        "Aplica fórmula Tanaka: 208 - 0.7 × edad",
        "Aplica fórmula Haskell: 220 - edad (tradicional)",
        "Compara com fórmulas Arena e Gulati para mujeres"
      ],
      "mistakes": [
        "Usar solo fórmula 220-edad (desactualizada, sobreestima em mayores)",
        "Entrenar siempre ao máximo (deve variar por zona de treinamento)",
        "Ignorar medicamentos que afectan frecuencia cardíaca (betabloqueadores)"
      ]
    },
    "de": {
      "name": "Rechner für Frequenz Cardíaca Máxima",
      "description": "Rechner Frequenz Cardiaca Max Gesundheit",
      "seo_title": "Rechner Frequenz Cardiaca Max Gesundheit | CalcToWork",
      "seo_description": "Rechner für Frequenz Cardíaca Máxima. Alter für berechnen Ihre FC máx. Tanaka, FC máx. Haskell, FC máx. Sand. Basado in die Formel von Gesundheit und",
      "desc": "Rechner für Frequenz Cardíaca Máxima. Alter für berechnen Ihre FC máx. Tanaka, FC máx. Haskell, FC máx. Sand. Basado in die Formel von Gesundheit und",
      "example_label": "Berechnetr Frequenz cardíaca máxima für Person von 30 Jahre",
      "range_hints": {
        "edad": "Geben Sie einen Wert ein"
      },
      "result_context": "Die verschiedene Formels producen variaciones von 5-10 bpm; Tanaka ist mehr präzise für adultos Maires",
      "steps": [
        "Geben Sie ein Alter in Jahre",
        "Aplica Formel Tanaka: 208 - 0.7 × Alter",
        "Aplica Formel Haskell: 220 - Alter (tradicional)",
        "Compara mit Formels Sand und Gulati für mujeres"
      ],
      "mistakes": [
        "Verwenden nur Formel 220-Alter (desactualizada, überschätzt in Maires)",
        "Entrenar immer zum Maximum (muss variar durch zona von entrenamiento)",
        "Ignorar médicamentos que afectan Frequenz cardíaca (betabloqueadores)"
      ],
      "formula_display": "Tanaka: FCmáx = 208 - 0.7 × Alter; Haskell: FCmáx = 220 - Alter",
      "inputs": {
        "edad": "Alter"
      },
      "outputs": {
        "fc_tanaka": "FC máx. Tanaka",
        "fc_haskell": "FC máx. Haskell",
        "fc_arena": "FC máx. Sand",
        "fc_gulati": "FC máx. Gulati"
      }
    },
    "it": {
      "name": "Body Fat Percentage Calculator (Marina)",
      "desc": "Calcola Max HR = 220 - age (classic formula). Esempio: 35-year-old person = Max HR = 185 bpm. Calcolatore gratuito e Preciso, senza registrazione.",
      "description": "Calcolatore Frequenza Cardiaca Max Salute",
      "seo_title": "Calcolatore Frequenza Cardiaca Max Salute",
      "seo_description": "Calcola Max HR = 220 - age (classic formula). Esempio: 35-year-old person = Max HR = 185 bpm. Calcolatore gratuito e Preciso, senza registrazione.",
      "inputs": {
        "edad": "Età"
      },
      "outputs": {
        "fc_tanaka": "FC max Tanaka",
        "fc_haskell": "FC max Haskell",
        "fc_arena": "FC max Arena",
        "fc_gulati": "FC max Gulati"
      },
      "example_label": "Calcolare frequenza cardíaca máxima per persona de 30 anni",
      "range_hints": {
        "edad": "Edad típica: 18-80"
      },
      "result_context": "Las diverse fórmulas producen variaciones de 5-10 bpm; Tanaka è più precisa per adultos mayores.",
      "formula_display": "Tanaka: FCmáx = 208 - 0.7 × edad; Haskell: FCmáx = 220 - edad",
      "steps": [
        "Ingresa edad en anni",
        "Aplica formula Tanaka: 208 - 0.7 × edad",
        "Aplica formula Haskell: 220 - edad (tradicional)",
        "Compara con fórmulas Sabbia e Gulati per mujeres"
      ],
      "mistakes": [
        "Usare solo formula 220-edad (desactualizada, sobreestima en mayores)",
        "Entrenar sempre al massimo (debe variar per zona de entrenamiento)",
        "Ignorare medicamentos que afectan frequenza cardíaca (betabloqueadores)"
      ]
    }
  }
}