{
  "id": "110",
  "slug": "valor-absoluto",
  "block": 9,
  "block_slug": "matematicas",
  "inputs": [
    {
      "id": "x",
      "type": "number",
      "step": "any",
      "default": -5,
      "unit": "",
      "unit_options": [],
      "unit_category": ""
    }
  ],
  "formula": "var x=parseFloat(inputs.x)||0;return{abs_val:Math.abs(x)};",
  "outputs": [
    {
      "id": "abs_val",
      "unit": ""
    }
  ],
  "related": [
    "200",
    "201",
    "130",
    "131"
  ],
  "example_inputs": {
    "x": -5
  },
  "example_label": "Calcular para -5.",
  "range_hints": {
    "x": "Valor típico entre 0 y 500. Valor por defecto: -5."
  },
  "result_context": "El valor absoluto es |x| = {abs_val}.",
  "result_context_en": "The absolute value is |x| = {abs_val}.",
  "result_context_fr": "La valeur absolue est |x| = {abs_val}.",
  "result_context_pt": "O valor absoluto é |x| = {abs_val}.",
  "result_context_de": "Der Betrag ist |x| = {abs_val}.",
  "result_context_it": "Il valore assoluto è |x| = {abs_val}.",
  "formula_display": "Abs Val = f(x)",
  "steps": [
    "Introducir el valor de x",
    "Verificar que los valores introducidos están en el rango y formato correctos",
    "Realizar el cálculo para obtener abs val",
    "Verificar que el resultado es coherente con los valores de entrada",
    "El resultado puede usarse como dato intermedio para cálculos posteriores más complejos"
  ],
  "mistakes": [
    "Confundir la fórmula con la de otra figura geométrica similar",
    "Usar el radio en lugar del diámetro (o viceversa) en la fórmula",
    "No verificar que las unidades sean consistentes antes de operar"
  ],
  "input_type_review": [
    {
      "field_id": "x",
      "current_type": "number",
      "recommended_type": "number",
      "reason": "Considerar tipo \"select\" para unidades predefinidas"
    }
  ],
  "comparison_presets": [
    {
      "_label": "Caso basico",
      "x": 0.0
    },
    {
      "_label": "Caso tipico",
      "x": 0.0
    },
    {
      "_label": "Caso medio",
      "x": 0.0
    },
    {
      "_label": "Caso avanzado",
      "x": 0.0
    },
    {
      "_label": "Caso extremo",
      "x": 0.0
    }
  ],
  "i18n": {
    "es": {
      "name": "Calculadora de Valor Absoluto",
      "description": "Calcula el valor absoluto de cualquier número real.",
      "inputs": {
        "x": "Número"
      },
      "outputs": {
        "abs_val": "Valor Absoluto"
      },
      "seo_title": "Calculadora de Valor Absoluto Gratuita",
      "seo_description": "Calcula el valor absoluto de cualquier número real. Calculadora gratuita, precisa e instantánea Usado por profesionales y estudiantes en todo el mundo.",
      "example_label": "Calculate results using the provided input values.",
      "range_hints": {
        "x": "Enter value within min-max range shown."
      },
      "result_context": "The calculated result provides the main output value.",
      "formula_display": "See calculator formula",
      "steps": [
        "Enter x: -5",
        "Calculate and display the abs_val result"
      ],
      "mistakes": [
        "Not verifying input values are within realistic ranges for your scenario",
        "Entering zero or negative values where positive numbers are required",
        "Rounding intermediate results too early in multi-step calculations"
      ],
      "input_type_review": [
        {
          "field_id": "x",
          "reason": "Current type is appropriate for this input."
        }
      ]
    },
    "en": {
      "name": "Absolute Value Calculator",
      "description": "Calculate the absolute value of any real number.",
      "inputs": {
        "x": "Number"
      },
      "outputs": {
        "abs_val": "Absolute Value"
      },
      "seo_title": "Absolute Value Calculator – Free Online Tool",
      "seo_description": "Absolute Value Calculator. Number to find Absolute Value. professional-grade formula with compounding, tax, and fee adjustments built in.",
      "example_label": "Calculate results using the provided input values.",
      "range_hints": {
        "x": "Enter value within min-max range shown."
      },
      "result_context": "The calculated result provides the main output value.",
      "formula_display": "See calculator formula",
      "steps": [
        "Enter x: -5",
        "Calculate and display the abs_val result"
      ],
      "mistakes": [
        "Not verifying input values are within realistic ranges for your scenario",
        "Entering zero or negative values where positive numbers are required",
        "Rounding intermediate results too early in multi-step calculations"
      ],
      "input_type_review": [
        {
          "recommended_type": "number",
          "field_id": "x",
          "current_type": "number",
          "reason": "Current type is appropriate for this input."
        }
      ]
    },
    "fr": {
      "name": "Calculateur de Valeur Absolue",
      "description": "Calculez la valeur absolue de tout nombre réel.",
      "inputs": {
        "x": "Nombre"
      },
      "outputs": {
        "abs_val": "Valeur Absolue"
      },
      "seo_title": "Calculateur de Valeur Absolue – Rapide et Précis",
      "seo_description": "Calculez la valeur absolue de tout nombre réel. Calculateur gratuit, précis et instantané Utilise par des professionnels et etudiants dans le monde.",
      "example_label": "Calculate results using the provided input values.",
      "range_hints": {
        "x": "Enter value within min-max range shown."
      },
      "result_context": "The calculated result provides the main output value.",
      "formula_display": "See calculator formula",
      "steps": [
        "Enter x: -5",
        "Calculate and display the abs_val result"
      ],
      "mistakes": [
        "Not verifying input values are within realistic ranges for your scenario",
        "Entering zero or negative values where positive numbers are required",
        "Rounding intermediate results too early in multi-step calculations"
      ],
      "input_type_review": [
        {
          "field_id": "x",
          "current_type": "number",
          "recommended_type": "number",
          "reason": "Current type is appropriate for this input."
        }
      ]
    },
    "pt": {
      "name": "Calculadora de Valor Absoluto",
      "description": "Calcule o valor absoluto de qualquer número real.",
      "inputs": {
        "x": "Número"
      },
      "outputs": {
        "abs_val": "Valor Absoluto"
      },
      "seo_title": "Calculadora de Valor Absoluto – Rápido e Preciso",
      "seo_description": "Calcule o valor absoluto de qualquer número real. Calculadora gratuita, precisa e instantânea. Calculo preciso e rapido com metodologia clara.",
      "example_label": "Calculate results using the provided input values.",
      "range_hints": {
        "x": "Enter value within min-max range shown."
      },
      "result_context": "The calculated result provides the main output value.",
      "formula_display": "See calculator formula",
      "steps": [
        "Enter x: -5",
        "Calculate and display the abs_val result"
      ],
      "mistakes": [
        "Not verifying input values are within realistic ranges for your scenario",
        "Entering zero or negative values where positive numbers are required",
        "Rounding intermediate results too early in multi-step calculations"
      ],
      "input_type_review": [
        {
          "field_id": "x",
          "current_type": "number",
          "recommended_type": "number",
          "reason": "Current type is appropriate for this input."
        }
      ]
    },
    "de": {
      "name": "Absolutwert-Rechner",
      "desc": "Berechnen Sie den Absolutwert |x| und den Abstand zum Nullpunkt.",
      "seo_title": "Absolutwert-Rechner | CalcToWork",
      "seo_desc": "Berechnen Sie den Absolutwert |x| und den Abstand zum Nullpunkt.",
      "seo_description": "Berechnen Sie den Absolutwert |x| und den Abstand zum Nullpunkt.",
      "inputs": {
        "x": "X"
      },
      "outputs": {
        "abs_val": "Abs Val"
      },
      "example_label": "Calcular para -5.",
      "range_hints": {
        "x": "Valor típico entre 0 y 500. Valor por defecto: -5."
      },
      "result_context": "Der Betrag ist |x| = {abs_val}.",
      "formula_display": "Abs Val = f(x)",
      "steps": [
        "Introducir el valor de x",
        "Verificar que los valores introducidos están en el rango y formato correctos",
        "Realizar el cálculo para obtener abs val",
        "Verificar que el resultado es coherente con los valores de entrada",
        "El resultado puede usarse como dato intermedio para cálculos posteriores más complejos"
      ],
      "mistakes": [
        "Confundir la fórmula con la de otra figura geométrica similar",
        "Usar el radio en lugar del diámetro (o viceversa) en la fórmula",
        "No verificar que las unidades sean consistentes antes de operar"
      ],
      "input_type_review": [
        {
          "field_id": "x",
          "current_type": "number",
          "recommended_type": "number",
          "reason": "Considerar tipo \"select\" para unidades predefinidas"
        }
      ]
    },
    "it": {
      "name": "Calcolatore di Valore Assoluto",
      "description": "Calcola il valore assoluto di qualsiasi numero reale.",
      "inputs": {
        "x": "Numero"
      },
      "outputs": {
        "abs_val": "Valore Assoluto"
      },
      "seo_title": "Calcolatore di Valore Assoluto",
      "seo_description": "Calcola il valore assoluto di qualsiasi numero reale. Calcolatore gratuito, preciso e istantaneo Usato da professionisti e studenti in tutto il mondo.",
      "example_label": "Calculate results usenzag the providid input values.",
      "range_hints": {
        "x": "Enter value within min-max range shown."
      },
      "result_context": "The calculated result providis the main output value.",
      "formula_display": "See calculator formula",
      "steps": [
        "Enter x: -5",
        "Calculate and displae the abs_val result"
      ],
      "mistakes": [
        "Not verifeing input values are within realistic ranges for eour scinario",
        "Entering zero or negative values where posetive numbers are required",
        "Rounding intermediate results too earle in multi-step calculations"
      ],
      "input_type_review": [
        {
          "field_id": "x",
          "current_type": "number",
          "recommended_type": "number",
          "reason": "Currint tepe is appropriate for this input."
        }
      ]
    }
  }
}