{
  "id": "420",
  "slug": "zonas-frecuencia-cardiaca",
  "block": 5,
  "block_slug": "salud",
  "inputs": [
    {
      "id": "age",
      "type": "number",
      "step": 1,
      "default": 30,
      "unit": "yr",
      "unit_options": [
        "yr"
      ],
      "unit_category": "time"
    }
  ],
  "formula": "var age=parseFloat(inputs.age)||0;var max_hr=220-age;var z1=Math.round(max_hr*0.5)+'-'+Math.round(max_hr*0.6);var z2=Math.round(max_hr*0.6)+'-'+Math.round(max_hr*0.7);var z3=Math.round(max_hr*0.7)+'-'+Math.round(max_hr*0.8);var z4=Math.round(max_hr*0.8)+'-'+Math.round(max_hr*0.9);var z5=Math.round(max_hr*0.9)+'-'+max_hr;return{zone1:z1,zone2:z2,zone3:z3,zone4:z4,zone5:z5};",
  "outputs": [
    {
      "id": "zone1",
      "unit": "bpm"
    },
    {
      "id": "zone2",
      "unit": "bpm"
    },
    {
      "id": "zone3",
      "unit": "bpm"
    },
    {
      "id": "zone4",
      "unit": "bpm"
    },
    {
      "id": "zone5",
      "unit": "bpm"
    }
  ],
  "related": [
    "419",
    "411",
    "421",
    "426"
  ],
  "example_inputs": {
    "age": 30
  },
  "comparison_presets": [
    {
      "_label": "Child",
      "age": 15
    },
    {
      "_label": "Teen",
      "age": 22
    },
    {
      "_label": "Adult (F)",
      "age": 30
    },
    {
      "_label": "Adult (M)",
      "age": 45
    },
    {
      "_label": "Elderly",
      "age": 60
    }
  ],
  "units": {
    "age": "s"
  },
  "i18n": {
    "es": {
      "name": "Zonas de Frecuencia Cardíaca",
      "description": "Calcula las 5 zonas de entrenamiento cardíaco basadas en la edad.",
      "inputs": {
        "age": "Edad"
      },
      "outputs": {
        "zone1": "Zona 1",
        "zone2": "Zona 2",
        "zone3": "Zona 3",
        "zone4": "Zona 4",
        "zone5": "Zona 5"
      },
      "seo_title": "Zonas de Frecuencia Cardíaca Gratuita",
      "seo_description": "Calcula las 5 zonas de entrenamiento cardíaco basadas en la edad. Calculadora gratuita, precisa e instantánea. Obten resultados al instante con.",
      "example_label": "Determinar zonas de frecuencia cardíaca para persona de 30 años",
      "range_hints": {
        "age": "Edad típica: 18-80 yr"
      },
      "result_context": "Zona 1-2 es quema de grasa, Zona 3-4 es cardio, Zona 5 es anaeróbico máximo para intervalos.",
      "formula_display": "Zona 1: 50-60% FCmáx; Zona 2: 60-70%; Zona 3: 70-80%; Zona 4: 80-90%; Zona 5: 90-100%",
      "steps": [
        "El calculador aplica la fórmula automáticamente y muestra resultados"
      ],
      "mistakes": [
        "No verificar que age estén en unidades correctas antes de calcular",
        "Redondear valores intermedios antes del cálculo final (pierde precisión)",
        "Aplicar resultados sin considerar contexto individual o condiciones especiales"
      ],
      "long_content": "<section class=\"long-content\">\n<h1>Calculadora de zonas de entrenamiento de frecuencia cardíaca: entrene de forma más inteligente</h1>\n<p>Las zonas de entrenamiento de frecuencia cardíaca dividen su frecuencia cardíaca máxima en cinco rangos de intensidad distintos, cada uno de los cuales apunta a diferentes adaptaciones fisiológicas y sistemas de energía. Entrenar en la zona correcta garantiza que obtenga el estímulo adecuado para sus objetivos de acondicionamiento físico específicos, ya sea desarrollar una base aeróbica, mejorar la resistencia o desarrollar el máximo rendimiento.</p>\n<p class=\"see-also\">También puede encontrar el<a href=\"/es/frecuencia-cardiaca-karvonen/\">Karvonen Heart Rate Calculator</a>, <a href=\"/es/frecuencia-cardiaca-max-salud/\">Max Heart Rate Health Calculator</a>, and <a href=\"/es/aclaramiento-creatinina/\">Creatinine Clearance (Cockcroft-Gault)</a> useful.</p><div class=\"formula-section\">\n<h2>Fórmula de zonas de entrenamiento de frecuencia cardíaca</h2>\n<p class=\"formula-display\">Zona 1: 50-60 % de FC máxima |  Zona 2: 60-70 % de FC máxima |  Zona 3: 70–80% FC máxima<br/>Zona 4: 80-90 % de FC máxima |  Zona 5: 90–100% FC máxima</p>\n<p>Primero calcule su frecuencia cardíaca máxima usando 220 − edad (o un valor medido de una prueba de ejercicio graduada). Luego calcula cada zona multiplicando tu FC máxima por el rango porcentual correspondiente. Para una persona de 35 años con una FC máxima estimada de 185 lpm: Zona 1 = 93–111 lpm (calentamiento/recuperación), Zona 2 = 111–130 lpm (quema de grasa/base aeróbica), Zona 3 = 130–148 lpm (resistencia aeróbica), Zona 4 = 148–167 lpm (umbral de lactato), Zona 5 = 167–185 lpm (esfuerzo máximo/anaeróbico).</p>\n</div>\n<div class=\"examples-section\">\n<h2>Ejemplos resueltos</h2>\n<div class=\"example\">\n<h3>Ejemplo 1: Plan de entrenamiento para maratón</h3>\n<p>Una persona de 40 años que se prepara para un maratón tiene una frecuencia cardíaca máxima de 180 ppm y quiere estructurar el entrenamiento semanal en varias zonas.</p>\n<p>Zona 2 (60–70%): 108–126 bpm — 3 carreras largas por semana<br/>Zona 3 (70–80%): 126–144 bpm — 1 ejecución de tempo por semana<br/>Zona 4 (80–90%): 144–162 bpm — 1 sesión de intervalo por semana</p>\n<p>Este enfoque polarizado dedica el 80% del tiempo de entrenamiento en la Zona 2 para el desarrollo aeróbico, mientras que utiliza las zonas más altas con moderación para el trabajo de umbral y velocidad. Esta distribución refleja los patrones de entrenamiento de los atletas de resistencia de élite.</p>\n</div>\n<div class=\"example\">\n<h3>Ejemplo 2: Sesión HIIT para perder grasa</h3>\n<p>Una mujer de 30 años con una FC máxima de 190 lpm diseña una sesión de entrenamiento interválico de alta intensidad.</p>\n<p>Calentamiento: Zona 1 (95–114 bpm) durante 5 minutos<br/>Intervalos de trabajo: Zona 5 (171–190 bpm) durante 30 segundos × 8 rondas<br/>Recuperación: Zona 2 (114–133 bpm) durante 90 segundos entre intervalos<br/>Enfriamiento: Zona 1 (95–114 bpm) durante 5 minutos</p>\n<p>Esta sesión de 28 minutos maximiza el EPOC (consumo excesivo de oxígeno post-ejercicio), creando una tasa metabólica elevada durante horas después del ejercicio. La alternancia entre la Zona 5 y la Zona 2 entrena tanto la capacidad anaeróbica como la eficiencia de recuperación.</p>\n</div>\n</div>\n<div class=\"uses-section\">\n<h2>Usos comunes</h2>\n<ul>\n<li>Estructurar programas de entrenamiento periodizados que desarrollen sistemáticamente diferentes sistemas energéticos a lo largo de una temporada</li>\n<li>Garantizar que los días fáciles sigan siendo realmente fáciles manteniendo las carreras de recuperación en la Zona 1–2</li>\n<li>Diseño de protocolos de entrenamiento interválico con objetivos precisos de frecuencia cardíaca de trabajo y recuperación</li>\n<li>Monitoreo de la carga de entrenamiento y prevención del sobreentrenamiento mediante análisis de distribución del tiempo basado en zonas</li>\n<li>Establecer la intensidad adecuada para las clases grupales de fitness para adaptarse a los diferentes niveles de fitness</li>\n<li>El seguimiento de las mejoras en el estado físico a medida que el mismo ritmo produce una frecuencia cardíaca más baja con el tiempo</li>\n</ul>\n</div>\n<div class=\"mistakes-section\">\n<h2>Errores comunes</h2>\n<ul>\n<li>Pasar demasiado tiempo en la Zona 3 (la “zona gris”), que es demasiado difícil para la recuperación pero demasiado fácil para una adaptación significativa</li>\n<li>Usar una estimación inexacta de la frecuencia cardíaca máxima que cambia todas las zonas incorrectamente, lo que lleva a un sobreentrenamiento o un subentrenamiento</li>\n<li>Ignorar que las zonas basadas en la FC máxima difieren de las zonas basadas en el umbral de lactato, que pueden ser de 10 a 20 lpm diferentes</li>\n<li>No ajustar las zonas a medida que mejora la condición física, lo que hace que el entrenamiento se vuelva progresivamente menos desafiante de lo previsto</li>\n</ul>\n</div>\n<div class=\"pro-tip\">\n<h2>Consejo profesional</h2>\n<p>Sigue la regla 80/20: dedica aproximadamente el 80 % de tu tiempo de entrenamiento semanal en las Zonas 1 y 2 y el 20 % en las Zonas 4 y 5. Este enfoque polarizado, validado por investigaciones sobre atletas de resistencia de élite, produce ganancias de condición física superiores en comparación con el entrenamiento de intensidad moderada. Utilice un monitor de frecuencia cardíaca con correa para el pecho para mayor precisión, ya que los sensores ópticos en la muñeca pueden retrasarse entre 5 y 15 segundos durante los cambios rápidos de intensidad, lo que hace que el seguimiento de la zona sea menos confiable durante las sesiones de intervalos.</p>\n</div>\n<div class=\"faq-section\">\n<h2>Preguntas frecuentes</h2>\n<div class=\"faq-list\">\n<div class=\"faq-item\">\n<button aria-expanded=\"false\" class=\"faq-q\">¿Debo utilizar la FC máxima o el umbral de lactato para los cálculos de zona?</button>\n<div class=\"faq-a\">Las zonas basadas en el umbral de lactato son más precisas para los atletas serios, ya que la frecuencia cardíaca umbral varía independientemente de la FC máxima. Sin embargo, las zonas de FC máxima son más sencillas de calcular y suficientes para los deportistas recreativos. Si tiene acceso a pruebas de umbral de lactato, utilice esos valores. De lo contrario, las zonas de FC máxima proporcionan una aproximación razonable.</div>\n</div>\n<div class=\"faq-item\">\n<button aria-expanded=\"false\" class=\"faq-q\">¿En qué zona deben entrenar los principiantes?</button>\n<div class=\"faq-a\">Los principiantes deben pasar la mayor parte del tiempo en la Zona 2 (60–70 % de la FC máxima) durante las primeras 8 a 12 semanas. Esto desarrolla la capacidad aeróbica, fortalece el sistema cardiovascular y desarrolla la eficiencia para quemar grasa sin fatiga excesiva ni riesgo de lesiones. Introduzca gradualmente el trabajo de la Zona 3 después de establecer una base aeróbica.</div>\n</div>\n<div class=\"faq-item\">\n<button aria-expanded=\"false\" class=\"faq-q\">¿Cuánto tiempo debo permanecer en la Zona 5 durante los intervalos?</button>\n<div class=\"faq-a\">Los esfuerzos de la zona 5 deben ser breves: de 30 segundos a 2 minutos como máximo por intervalo, con recuperación total entre esfuerzos. La zona 5 representa un esfuerzo casi máximo a máximo y no puede mantenerse durante largos períodos. Las sesiones típicas de HIIT incluyen de 6 a 12 intervalos de la Zona 5 con períodos de recuperación iguales o más largos en la Zona 1-2.</div>\n</div>\n<div class=\"faq-item\">\n<button aria-expanded=\"false\" class=\"faq-q\">¿Las zonas de frecuencia cardíaca cambian con la edad?</button>\n<div class=\"faq-a\">Sí. Dado que la frecuencia cardíaca máxima disminuye aproximadamente 1 lpm por año, los límites absolutos de su zona disminuyen con la edad. Vuelve a calcular tus zonas anualmente o cada vez que notes un cambio constante en tu FC máxima. Sin embargo, los límites porcentuales (50–60%, 60–70%, etc.) siguen siendo los mismos independientemente de la edad.</div>\n</div>\n</div>\n</div>\n<div class=\"related-calculators\">\n<h2>Calculadoras relacionadas</h2>\n<ul> <li><a href=\"/es/frecuencia-cardiaca-karvonen/\">Karvonen Heart Rate Calculator</a></li>\n<li><a href=\"/es/\">BMR (Harris-Benedict) Calculator</a></li>\n<li><a href=\"/es/\">BMR (Katch-McArdle) Calculator</a></li>\n<li><a href=\"/es/\">Weight Loss Calculator</a></li>\n<li><a href=\"/es/heart-rate-zones/\">Heart Rate Zones Calculator</a></li>\n</ul>\n</div>\n</section>\n"
    },
    "en": {
      "name": "Heart Rate Zones Calculator",
      "description": "Calculate heart rate training zones.",
      "inputs": {
        "age": "Age"
      },
      "outputs": {
        "zone1": "Zone 1",
        "zone2": "Zone 2",
        "zone3": "Zone 3",
        "zone4": "Zone 4",
        "zone5": "Zone 5"
      },
      "seo_title": "Heart Rate Training Zones – Fast & Accurate",
      "seo_description": "Use our free heart rate training zones to quickly estimate zone1, zone2 based on age. No registration needed.",
      "example_label": "Calculate HR zones for 30 year old.",
      "range_hints": {
        "age": "Edad típica: 18-80 yr"
      },
      "result_context": "Zona 1-2 es quema of grasa, Zona 3-4 es cardio, Zona 5 es anaeróbico maximum to intervalos.",
      "formula_display": "Zona 1: 50-60% FCmáx; Zona 2: 60-70%; Zona 3: 70-80%; Zona 4: 80-90%; Zona 5: 90-100%",
      "steps": [
        "The calculador aplica The formula automatically and muestra results"
      ],
      "mistakes": [
        "No Verify que age estén in units correctas antes of Calculate",
        "Redondear values intermedios antes of the calculation final (pierde precisión)",
        "Apply results without Consider contexto individual or condiciones especiales"
      ],
      "long_content": "<section class=\"long-content\">\n  <h1>Heart Rate Training Zones Calculator: Train Smarter</h1>\n  <p>Heart rate training zones divide your maximum heart rate into five distinct intensity ranges, each targeting different physiological adaptations and energy systems. Training in the correct zone ensures you get the right stimulus for your specific fitness goals, whether that&rsquo;s building an aerobic base, improving endurance, or developing peak performance.</p>\n  <p class=\"see-also\">You may also find the <a href=\"/en/credit-card-payoff/\">Karvonen Heart Rate Calculator</a>, <a href=\"/en/quemar-calorias-met/\">Max Heart Rate Health Calculator</a>, and <a href=\"/en/momento-inercia/\">Creatinine Clearance (Cockcroft-Gault)</a> useful.</p>\n  <!-- internal-links-added -->\n\n  <div class=\"formula-section\">\n    <h2>Heart Rate Training Zones Formula</h2>\n    <p class=\"formula-display\">Zone 1: 50&ndash;60% Max HR &nbsp;|&nbsp; Zone 2: 60&ndash;70% Max HR &nbsp;|&nbsp; Zone 3: 70&ndash;80% Max HR<br>Zone 4: 80&ndash;90% Max HR &nbsp;|&nbsp; Zone 5: 90&ndash;100% Max HR</p>\n    <p>First estimate your maximum heart rate using 220 &minus; age (or a measured value from a graded exercise test). Then calculate each zone by multiplying your max HR by the corresponding percentage range. For a 35-year-old with an estimated max HR of 185 bpm: Zone 1 = 93&ndash;111 bpm (warm-up/recovery), Zone 2 = 111&ndash;130 bpm (fat burning/aerobic base), Zone 3 = 130&ndash;148 bpm (aerobic endurance), Zone 4 = 148&ndash;167 bpm (lactate threshold), Zone 5 = 167&ndash;185 bpm (maximum effort/anaerobic).</p>\n  </div>\n\n  <div class=\"examples-section\">\n    <h2>Worked Examples</h2>\n    <div class=\"example\">\n      <h3>Example 1: Marathon Training Plan</h3>\n      <p>A 40-year-old preparing for a marathon has a max HR of 180 bpm and wants to structure weekly training across zones.</p>\n      <p>Zone 2 (60&ndash;70%): 108&ndash;126 bpm &mdash; 3 long runs per week<br>Zone 3 (70&ndash;80%): 126&ndash;144 bpm &mdash; 1 tempo run per week<br>Zone 4 (80&ndash;90%): 144&ndash;162 bpm &mdash; 1 interval session per week</p>\n      <p>This polarized approach spends 80% of training time in Zone 2 for aerobic development while using higher zones sparingly for threshold and speed work. This distribution mirrors the training patterns of elite endurance athletes.</p>\n    </div>\n    <div class=\"example\">\n      <h3>Example 2: HIIT Session for Fat Loss</h3>\n      <p>A 30-year-old woman with a max HR of 190 bpm designs a high-intensity interval training session.</p>\n      <p>Warm-up: Zone 1 (95&ndash;114 bpm) for 5 minutes<br>Work intervals: Zone 5 (171&ndash;190 bpm) for 30 seconds &times; 8 rounds<br>Recovery: Zone 2 (114&ndash;133 bpm) for 90 seconds between intervals<br>Cool-down: Zone 1 (95&ndash;114 bpm) for 5 minutes</p>\n      <p>This 28-minute session maximizes EPOC (excess post-exercise oxygen consumption), creating an elevated metabolic rate for hours after exercise. The alternating between Zone 5 and Zone 2 trains both anaerobic capacity and recovery efficiency.</p>\n    </div>\n  </div>\n\n  <div class=\"uses-section\">\n    <h2>Common Uses</h2>\n    <ul>\n      <li>Structuring periodized training programs that systematically develop different energy systems over a season</li>\n      <li>Ensuring easy days stay truly easy by keeping recovery runs in Zone 1&ndash;2</li>\n      <li>Designing interval training protocols with precise work and recovery heart rate targets</li>\n      <li>Monitoring training load and preventing overtraining through zone-based time distribution analysis</li>\n      <li>Setting appropriate intensity for group fitness classes to accommodate varying fitness levels</li>\n      <li>Tracking fitness improvements as the same pace produces a lower heart rate over time</li>\n    </ul>\n  </div>\n\n  <div class=\"mistakes-section\">\n    <h2>Common Mistakes</h2>\n    <ul>\n      <li>Spending too much time in Zone 3 (the &ldquo;grey zone&rdquo;), which is too hard for recovery but too easy for meaningful adaptation</li>\n      <li>Using an inaccurate maximum heart rate estimate that shifts all zones incorrectly, leading to undertraining or overtraining</li>\n      <li>Ignoring that zones based on max HR differ from zones based on lactate threshold, which can be 10&ndash;20 bpm different</li>\n      <li>Not adjusting zones as fitness improves, causing training to become progressively less challenging than intended</li>\n    </ul>\n  </div>\n\n  <div class=\"pro-tip\">\n    <h2>Pro Tip</h2>\n    <p>Follow the 80/20 rule: spend approximately 80% of your weekly training time in Zones 1&ndash;2 and 20% in Zones 4&ndash;5. This polarized approach, validated by research on elite endurance athletes, produces superior fitness gains compared to moderate-intensity training. Use a chest-strap heart rate monitor for accuracy, as wrist-based optical sensors can lag by 5&ndash;15 seconds during rapid intensity changes, making zone tracking less reliable during interval sessions.</p>\n  </div>\n\n  <div class=\"faq-section\">\n    <h2>Frequently Asked Questions</h2>\n    <div class=\"faq-list\">\n      <div class=\"faq-item\">\n        <button class=\"faq-q\" aria-expanded=\"false\">Should I use max HR or lactate threshold for zone calculations?</button>\n        <div class=\"faq-a\">Lactate threshold-based zones are more accurate for serious athletes, as threshold heart rate varies independently of max HR. However, max HR zones are simpler to calculate and sufficient for recreational exercisers. If you have access to lactate threshold testing, use those values. Otherwise, max HR zones provide a reasonable approximation.</p></div>\n      </div>\n      <div class=\"faq-item\">\n        <button class=\"faq-q\" aria-expanded=\"false\">What zone should beginners train in?</button>\n        <div class=\"faq-a\">Beginners should spend most of their time in Zone 2 (60&ndash;70% max HR) for the first 8&ndash;12 weeks. This builds aerobic capacity, strengthens the cardiovascular system, and develops fat-burning efficiency without excessive fatigue or injury risk. Gradually introduce Zone 3 work after establishing an aerobic base.</p></div>\n      </div>\n      <div class=\"faq-item\">\n        <button class=\"faq-q\" aria-expanded=\"false\">How long should I stay in Zone 5 during intervals?</button>\n        <div class=\"faq-a\">Zone 5 efforts should be brief: 30 seconds to 2 minutes maximum per interval, with full recovery between efforts. Zone 5 represents near-maximal to maximal effort and cannot be sustained for long periods. Typical HIIT sessions include 6&ndash;12 Zone 5 intervals with equal or longer recovery periods in Zone 1&ndash;2.</p></div>\n      </div>\n      <div class=\"faq-item\">\n        <button class=\"faq-q\" aria-expanded=\"false\">Do heart rate zones change with age?</button>\n        <div class=\"faq-a\">Yes. Since maximum heart rate decreases by approximately 1 bpm per year, your absolute zone boundaries shift downward with age. Recalculate your zones annually or whenever you notice a consistent change in your max HR. However, the percentage boundaries (50&ndash;60%, 60&ndash;70%, etc.) remain the same regardless of age.</p></div>\n      </div>\n    </div>\n  </div>\n\n  <div class=\"related-calculators\">\n    <h2>Related Calculators</h2>\n    <ul>      <li><a href=\"/en/karvonen-heart-rate/\">Karvonen Heart Rate Calculator</a></li>\n      <li><a href=\"/en/bmr-harris-benedict/\">BMR (Harris-Benedict) Calculator</a></li>\n      <li><a href=\"/en/bmr-katch-mcardle/\">BMR (Katch-McArdle) Calculator</a></li>\n      <li><a href=\"/en/mets-calculator/\">Weight Loss Calculator</a></li>\n      <li><a href=\"/en/permutations-calculator/\">Heart Rate Zones Calculator</a></li>\n    </ul>\n  </div>\n\n  \n</section>\n",
      "desc": "Free online heart rate training zones. Enter age to get instant results."
    },
    "fr": {
      "name": "Zones de Fréquence Cardiaque",
      "description": "Calculez les 5 zones d'entraînement cardiaque basées sur l'âge.",
      "inputs": {
        "age": "Âge"
      },
      "outputs": {
        "zone1": "Zone 1",
        "zone2": "Zone 2",
        "zone3": "Zone 3",
        "zone4": "Zone 4",
        "zone5": "Zone 5"
      },
      "seo_title": "Zones de Fréquence Cardiaque – Outil Gratuit",
      "seo_description": "Calculez les 5 zones d'entraînement cardiaque basées sur l'âge. Calculateur gratuit, précis et instantané. Obtenez des resultats instantanes avec.",
      "example_label": "Determiner zonas de fréquence cardíaca pour persona de ans",
      "range_hints": {
        "age": "Edad typique: 18-80 yr"
      },
      "result_context": "Zona 1-est quema de grasa, Zona 3-est cardio, Zona est anaeróbico maximum pour intervalos.",
      "formula_display": "Zona 1: 50-60% FCmáx; Zona 2: 60-70%; Zona 3: 70-80%; Zona 4: 80-90%; Zona 5: 90-100%",
      "steps": [
        "Le calculedor aplica La formule automatiquement et affiche resultats"
      ],
      "mistakes": [
        "No Verifier que age estén en unites correctas avant de Calculer",
        "Arrondir valeurs intermedios avant du calcul Final (pierde precisión)",
        "Appliquer resultats sans Considerer contexto individual ou condiciones especiales"
      ],
      "long_content": "<section class=\"long-content\">\n<h1>Calculateur de zones d'entraînement de fréquence cardiaque : entraînez-vous plus intelligemment</h1>\n<p>Les zones d'entraînement de fréquence cardiaque divisent votre fréquence cardiaque maximale en cinq plages d'intensité distinctes, chacune ciblant différentes adaptations physiologiques et systèmes énergétiques. L'entraînement dans la bonne zone garantit que vous obtenez le bon stimulus pour vos objectifs de remise en forme spécifiques, qu'il s'agisse de développer une base aérobique, d'améliorer votre endurance ou de développer des performances optimales.</p>\n<p class=\"see-also\">Vous pouvez également trouver le<a href=\"/en/credit-card-payoff/\">Karvonen Heart Rate Calculator</a>, <a href=\"/en/quemar-calorias-met/\">Max Heart Rate Health Calculator</a>, and <a href=\"/en/momento-inercia/\">Creatinine Clearance (Cockcroft-Gault)</a> useful.</p>\nliens-internes-ajoutés\n<div class=\"formula-section\">\n<h2>Formule de zones d'entraînement de fréquence cardiaque</h2>\n<p class=\"formula-display\">Zone 1 : 50 à 60 % de FC maximale |  Zone 2 : 60 à 70 % de FC maximale |  Zone 3 : 70 à 80 % de FC maximale<br/>Zone 4 : 80 à 90 % de FC maximale |  Zone 5 : 90 à 100 % de FC maximale</p>\n<p>Estimez d’abord votre fréquence cardiaque maximale en utilisant un âge de 220 − (ou une valeur mesurée à partir d’un test d’effort progressif). Calculez ensuite chaque zone en multipliant votre FC maximale par la plage de pourcentage correspondante. Pour une personne de 35 ans avec une fréquence cardiaque maximale estimée à 185 bpm : Zone 1 = 93 à 111 bpm (échauffement/récupération), Zone 2 = 111 à 130 bpm (combustion des graisses/base aérobie), Zone 3 = 130 à 148 bpm (endurance aérobie), Zone 4 = 148 à 167 bpm (seuil de lactate), Zone 5 = 167-185 bpm (effort maximum/anaérobie).</p>\n</div>\n<div class=\"examples-section\">\n<h2>Exemples travaillés</h2>\n<div class=\"example\">\n<h3>Exemple 1 : Plan d'entraînement marathon</h3>\n<p>Un homme de 40 ans se préparant pour un marathon a une FC maximale de 180 bpm et souhaite structurer son entraînement hebdomadaire sur plusieurs zones.</p>\n<p>Zone 2 (60-70 %) : 108-126 bpm — 3 longues courses par semaine<br/>Zone 3 (70 à 80 %) : 126 à 144 bpm — 1 course au tempo par semaine<br/>Zone 4 (80-90 %) : 144-162 bpm — 1 séance d'intervalles par semaine</p>\n<p>Cette approche polarisée consacre 80 % du temps d’entraînement dans la zone 2 pour le développement aérobie tout en utilisant avec parcimonie les zones plus élevées pour le travail au seuil et à la vitesse. Cette répartition reflète les schémas d’entraînement des athlètes d’endurance d’élite.</p>\n</div>\n<div class=\"example\">\n<h3>Exemple 2 : Séance HIIT pour la perte de graisse</h3>\n<p>Une femme de 30 ans avec une fréquence cardiaque maximale de 190 bpm conçoit une séance d'entraînement fractionné de haute intensité.</p>\n<p>Échauffement : Zone 1 (95-114 bpm) pendant 5 minutes<br/>Intervalles de travail : Zone 5 (171-190 bpm) pendant 30 secondes × 8 tours<br/>Récupération : Zone 2 (114-133 bpm) pendant 90 secondes entre les intervalles<br/>Récupération : Zone 1 (95-114 bpm) pendant 5 minutes</p>\n<p>Cette séance de 28 minutes maximise l'EPOC (consommation excessive d'oxygène après l'exercice), créant un taux métabolique élevé pendant des heures après l'exercice. L'alternance entre la Zone 5 et la Zone 2 entraîne à la fois la capacité anaérobie et l'efficacité de la récupération.</p>\n</div>\n</div>\n<div class=\"uses-section\">\n<h2>Utilisations courantes</h2>\n<ul>\n<li>Structuration de programmes de formation périodisés qui développent systématiquement différents systèmes énergétiques sur une saison</li>\n<li>Garantir que les journées faciles restent vraiment faciles en gardant les courses de récupération dans la zone 1–2</li>\n<li>Concevoir des protocoles d'entraînement fractionné avec des objectifs précis de fréquence cardiaque de travail et de récupération</li>\n<li>Surveillance de la charge d'entraînement et prévention du surentraînement grâce à une analyse de la répartition du temps par zone</li>\n<li>Définir l'intensité appropriée pour les cours de conditionnement physique en groupe afin de s'adapter à différents niveaux de condition physique</li>\n<li>Le suivi des améliorations de la condition physique au même rythme produit une fréquence cardiaque plus faible au fil du temps</li>\n</ul>\n</div>\n<div class=\"mistakes-section\">\n<h2>Erreurs courantes</h2>\n<ul>\n<li>Passer trop de temps dans la zone 3 (la « zone grise »), qui est trop difficile pour la récupération mais trop facile pour une adaptation significative</li>\n<li>Utilisation d'une estimation inexacte de la fréquence cardiaque maximale qui décale toutes les zones de manière incorrecte, entraînant un sous-entraînement ou un surentraînement</li>\n<li>Ignorer le fait que les zones basées sur la FC maximale diffèrent des zones basées sur le seuil de lactate, qui peuvent être différentes de 10 à 20 bpm</li>\n<li>Ne pas ajuster les zones à mesure que la condition physique s'améliore, ce qui rend l'entraînement progressivement moins difficile que prévu</li>\n</ul>\n</div>\n<div class=\"pro-tip\">\n<h2>Pro Tip</h2>\n<p>Suivez la règle des 80/20 : passez environ 80 % de votre temps d'entraînement hebdomadaire dans les zones 1 à 2 et 20 % dans les zones 4 à 5. Cette approche polarisée, validée par des recherches sur des athlètes d’endurance d’élite, produit des gains de condition physique supérieurs à ceux d’un entraînement d’intensité modérée. Utilisez un moniteur de fréquence cardiaque à ceinture pectorale pour plus de précision, car les capteurs optiques au poignet peuvent être en retard de 5 à 15 secondes lors de changements rapides d'intensité, ce qui rend le suivi de zone moins fiable pendant les séances d'intervalles.</p>\n</div>\n<div class=\"faq-section\">\n<h2>Foire aux questions</h2>\n<div class=\"faq-list\">\n<div class=\"faq-item\">\n<button aria-expanded=\"false\" class=\"faq-q\">Dois-je utiliser la FC maximale ou le seuil de lactate pour les calculs de zones ?</button>\n<div class=\"faq-a\">Les zones basées sur le seuil de lactate sont plus précises pour les athlètes sérieux, car le seuil de fréquence cardiaque varie indépendamment de la FC maximale. Cependant, les zones de FC maximales sont plus simples à calculer et suffisantes pour les sportifs récréatifs. Si vous avez accès aux tests de seuil lactate, utilisez ces valeurs. Sinon, les zones HR maximales fournissent une approximation raisonnable.</div>\n</div>\n<div class=\"faq-item\">\n<button aria-expanded=\"false\" class=\"faq-q\">Dans quelle zone les débutants doivent-ils s’entraîner ?</button>\n<div class=\"faq-a\">Les débutants devraient passer la plupart de leur temps dans la zone 2 (FC maximale de 60 à 70 %) pendant les 8 à 12 premières semaines. Cela développe la capacité aérobie, renforce le système cardiovasculaire et développe l’efficacité de la combustion des graisses sans fatigue excessive ni risque de blessure. Introduisez progressivement le travail en zone 3 après avoir établi une base aérobie.</div>\n</div>\n<div class=\"faq-item\">\n<button aria-expanded=\"false\" class=\"faq-q\">Combien de temps dois-je rester dans la zone 5 pendant les intervalles ?</button>\n<div class=\"faq-a\">Les efforts de la zone 5 doivent être brefs : 30 secondes à 2 minutes maximum par intervalle, avec une récupération complète entre les efforts. La zone 5 représente un effort presque maximal ou maximal et ne peut pas être maintenue pendant de longues périodes. Les séances HIIT typiques comprennent 6 à 12 intervalles de zone 5 avec des périodes de récupération égales ou plus longues dans la zone 1 à 2.</div>\n</div>\n<div class=\"faq-item\">\n<button aria-expanded=\"false\" class=\"faq-q\">Les zones de fréquence cardiaque changent-elles avec l’âge ?</button>\n<div class=\"faq-a\">Oui. Étant donné que la fréquence cardiaque maximale diminue d'environ 1 bpm par an, les limites absolues de vos zones diminuent avec l'âge. Recalculez vos zones chaque année ou chaque fois que vous remarquez un changement constant dans votre FC maximale. Cependant, les limites de pourcentage (50 à 60 %, 60 à 70 %, etc.) restent les mêmes quel que soit l'âge.</div>\n</div>\n</div>\n</div>\n<div class=\"related-calculators\">\n<h2>Calculatrices associées</h2>\n<ul> <li><a href=\"/en/karvonen-heart-rate/\">Karvonen Heart Rate Calculator</a></li>\n<li><a href=\"/en/bmr-harris-benedict/\">BMR (Harris-Benedict) Calculator</a></li>\n<li><a href=\"/en/bmr-katch-mcardle/\">BMR (Katch-McArdle) Calculator</a></li>\n<li><a href=\"/en/mets-calculator/\">Weight Loss Calculator</a></li>\n<li><a href=\"/en/permutations-calculator/\">Heart Rate Zones Calculator</a></li>\n</ul>\n</div>\n</section>\n"
    },
    "pt": {
      "name": "Zonas de Frequência Cardíaca",
      "description": "Calcule as 5 zonas de treino cardíaco com base na idade.",
      "inputs": {
        "age": "Idade"
      },
      "outputs": {
        "zone1": "Zona 1",
        "zone2": "Zona 2",
        "zone3": "Zona 3",
        "zone4": "Zona 4",
        "zone5": "Zona 5"
      },
      "seo_title": "Zonas de Frequência Cardíaca – Ferramenta Grátis",
      "seo_description": "Calcule as 5 zonas de treino cardíaco com base na idade. Calculadora gratuita, precisa e instantânea. Obtenha resultados instantaneos com explicacao.",
      "example_label": "Determinar zonas de frecuencia cardíaca para persona de 30 anos",
      "range_hints": {
        "age": "Edad típica: 18-80 yr"
      },
      "result_context": "Zona 1-2 é quema de grasa, Zona 3-4 é cardio, Zona 5 é anaeróbico máximo para intervalos.",
      "formula_display": "Zona 1: 50-60% FCmáx; Zona 2: 60-70%; Zona 3: 70-80%; Zona 4: 80-90%; Zona 5: 90-100%",
      "steps": [
        "El calculador aplica a fórmula automaticamente e muestra resultados"
      ],
      "mistakes": [
        "Não verificar que age estén em unidades correctas antes de calcular",
        "Reondear valores intermedios antes do cálculo final (pierde precisión)",
        "Aplicar resultados sem considerar contexto individual o condiciones especiais"
      ],
      "long_content": "<section class=\"long-content\">\n<h2>Como funciona o calculo</h2>\n<p>Seja para planejar uma reforma, estimar materiais para uma obra ou calcular dimensoes para um projeto DIY, ter os numeros certos desde o inicio economiza tempo e dinheiro.</p>\n<p>A formula por tras deste calculo e <strong>Zonas de Frequência Cardíaca = f(Idade)</strong>. Compreender como o resultado e obtido ajuda a verificar a saida e detectar erros de entrada.</p>\n\n<h2>Guia passo a passo para seu projeto</h2>\n<p>Siga estes passos para obter um resultado confiável:</p>\n<ol>\n<li><strong>Insira seus dados:</strong> 30 yr — ensure all values use a single consistent unit system.</li>\n<li><strong>A calculadora aplica a fórmula:</strong> <em>Zonas de Frequência Cardíaca = f(Idade)</em>.</li>\n<li><strong>Leia seu resultado:</strong> Zona 1, Zona 2, Zona 3.</li>\n<li>Verifique: confirme que as unidades são consistentes e os valores realistas antes de agir com base no resultado.</li>\n</ol>\n\n<h2>Usos praticos na obra</h2>\n<p>Esta calculadora é especialmente útil nas seguintes situações:</p>\n<ul>\n<li>acompanhamento de saúde e fitness</li><li>planejamento de nutrição e dieta</li><li>estimativa de parâmetros médicos</li><li>definição de metas de bem-estar</li>\n</ul>\n\n<h2>Como aplicar os resultados</h2>\n<p>Seu resultado mostra a quantidade teórica necessária. Antes de pedir, aplique o fator de perda adequado: 5–10&nbsp;% para concreto e argamassa, 10–15&nbsp;% para cerâmica, pedra natural e tijolo, e 3–5&nbsp;% para aço e madeira. Sempre arredonde para cima à próxima unidade inteira — saco, tonelada ou palete.</p>\n\n<h2>Normas de construção e boas práticas</h2>\n<p>Projetos de construção dependem de estimativas precisas de materiais para cumprir orçamento e cronograma. Profissionais geralmente adicionam 5–10&nbsp;% de margem de perda sobre a quantidade teórica para cobrir cortes, quebras e erros de medição. As normas ISO e ABNT definem as propriedades dos materiais utilizadas nestas fórmulas.</p>\n\n<h2>Erros comuns a evitar</h2>\n<ul>\n<li>Esquecer de adicionar margem de desperdicio (5-10%) ao pedir materiais.</li><li>Misturar unidades metricas e imperiais no mesmo projeto.</li>\n</ul>\n\n<h2>Dica profissional para contratados</h2>\n<p>Peça 5-10% mais material do que o calculo indica para cobrir cortes, quebras e erros de medicao.</p>\n\n<h2>Perguntas frequentes</h2>\n<div class=\"faq-list\">\n<div class=\"faq-item\"><button class=\"faq-q\" aria-expanded=\"false\">Quanto material extra devo pedir?</button><div class=\"faq-a\">A maioria dos profissionais recomenda pedir 5-10% mais do que o calculado para cobrir cortes e desperdicio.</p></div></div>\n<div class=\"faq-item\"><button class=\"faq-q\" aria-expanded=\"false\">Esta calculadora e precisa?</button><div class=\"faq-a\">Sim. A calculadora usa a formula padrao: Zonas de Frequência Cardíaca = f(Idade). Os resultados sao matematicamente exatos.</p></div></div>\n<div class=\"faq-item\"><button class=\"faq-q\" aria-expanded=\"false\">Posso usar esta calculadora no celular?</button><div class=\"faq-a\">Sim, a calculadora e totalmente responsiva e funciona em qualquer dispositivo.</p></div></div>\n<div class=\"faq-item\"><button class=\"faq-q\" aria-expanded=\"false\">Como salvo ou compartilho meu cálculo?</button><div class=\"faq-a\">Use o botão <strong>Compartilhar</strong> para gerar uma URL com todos os seus dados. O botão <strong>Copiar</strong> copia o resultado para a área de transferência.</p></div></div>\n<div class=\"faq-item\"><button class=\"faq-q\" aria-expanded=\"false\">O que fazer se o resultado parecer errado?</button><div class=\"faq-a\">Verifique suas entradas: valores nas unidades corretas e faixa realista. Confirme também que a fórmula <em>Zonas de Frequência Cardíaca = f(Idade)</em> se aplica exatamente à sua situação.</p></div></div>\n</div>\n</section>"
    },
    "de": {
      "name": "Trainingszonen (detailliert)",
      "description": "Berechnen Sie trainingszonen Herzfrequenz cardiaca online. Geben Sie age ein und erhalten Sie sofort das Ergebnis.",
      "seo_title": "Trainingszonen (detailliert) | CalcToWork",
      "seo_description": "Trainingszonen Herzfrequenz cardiaca online berechnen. Einfach Werte eingeben, Ergebnis sofort erhalten. Kostenlos und ohne Registrierung.",
      "desc": "Berechnen Sie trainingszonen Herzfrequenz cardiaca online. Geben Sie age ein und erhalten Sie sofort das Ergebnis.",
      "example_label": "Bestimmen Zonen von Frequenz cardíaca für Person von 30 Jahre",
      "range_hints": {
        "age": "Geben Sie einen Wert ein"
      },
      "result_context": "Zona 1-2 ist quema von Fett, Zona 3-4 ist cardio, Zona 5 ist anaeróbico Maximum für intervalos",
      "steps": [
        "Der Rechner wendet die Formel automatisch an und zeigt Ergebnisse"
      ],
      "mistakes": [
        "No überprüfen que age estén in Einheiten correctas antes von berechnen",
        "Zwischenwerte vor Endberechnung runden (Genauigkeitsverlust)",
        "Ergebnisse ohne Berücksichtigung von Einzelfall oder Sonderbedingungen anwenden"
      ],
      "formula_display": "Zona 1: 50-60% FCmáx; Zona 2: 60-70%; Zona 3: 70-80%; Zona 4: 80-90%; Zona 5: 90-100%",
      "inputs": {
        "age": "Alter"
      },
      "outputs": {
        "zone1": "Zona 1",
        "zone2": "Zona 2",
        "zone3": "Zona 3",
        "zone4": "Zona 4",
        "zone5": "Zona 5"
      },
      "long_content": "<section class=\"long-content\">\n<h1>Herzfrequenz-Trainingszonen-Rechner: Intelligenter trainieren</h1>\n<p>Herzfrequenz-Trainingszonen unterteilen Ihre maximale Herzfrequenz in fünf verschiedene Intensitätsbereiche, die jeweils auf unterschiedliche physiologische Anpassungen und Energiesysteme abzielen. Das Training in der richtigen Zone stellt sicher, dass Sie den richtigen Reiz für Ihre spezifischen Fitnessziele erhalten, sei es der Aufbau einer aeroben Basis, die Verbesserung der Ausdauer oder die Entwicklung von Höchstleistungen.</p>\n<p class=\"see-also\">Möglicherweise finden Sie auch<a href=\"/en/credit-card-payoff/\">Karvonen Heart Rate Calculator</a>, <a href=\"/en/quemar-calorias-met/\">Max Heart Rate Health Calculator</a>, and <a href=\"/en/momento-inercia/\">Creatinine Clearance (Cockcroft-Gault)</a> useful.</p>\ninternal-links-added\n<div class=\"formula-section\">\n<h2>Formel für Herzfrequenz-Trainingszonen</h2>\n<p class=\"formula-display\">Zone 1: 50–60 % maximale Herzfrequenz  |  Zone 2: 60–70 % maximale Herzfrequenz  |  Zone 3: 70–80 % maximale Herzfrequenz<br/>Zone 4: 80–90 % maximale Herzfrequenz  |  Zone 5: 90–100 % maximale Herzfrequenz</p>\n<p>Schätzen Sie zunächst Ihre maximale Herzfrequenz anhand des Alters (oder eines Messwerts aus einem benoteten Belastungstest). Berechnen Sie dann jede Zone, indem Sie Ihre maximale Herzfrequenz mit dem entsprechenden Prozentbereich multiplizieren. Für einen 35-Jährigen mit einer geschätzten maximalen Herzfrequenz von 185 Schlägen pro Minute: Zone 1 = 93–111 Schläge pro Minute (Aufwärmen/Erholung), Zone 2 = 111–130 Schläge pro Minute (Fettverbrennung/aerobe Basis), Zone 3 = 130–148 Schläge pro Minute (aerobe Ausdauer), Zone 4 = 148–167 Schläge pro Minute (Laktatschwelle), Zone 5 = 167–185 Schläge pro Minute (maximale Anstrengung/anaerob).</p>\n</div>\n<div class=\"examples-section\">\n<h2>Ausgearbeitete Beispiele</h2>\n<div class=\"example\">\n<h3>Beispiel 1: Marathon-Trainingsplan</h3>\n<p>Ein 40-Jähriger, der sich auf einen Marathon vorbereitet, hat eine maximale Herzfrequenz von 180 Schlägen pro Minute und möchte das wöchentliche Training zonenübergreifend strukturieren.</p>\n<p>Zone 2 (60–70 %): 108–126 Schläge pro Minute – 3 lange Läufe pro Woche<br/>Zone 3 (70–80 %): 126–144 Schläge pro Minute – 1 Tempolauf pro Woche<br/>Zone 4 (80–90 %): 144–162 Schläge pro Minute – 1 Intervallsitzung pro Woche</p>\n<p>Dieser polarisierte Ansatz verbringt 80 % der Trainingszeit in Zone 2 für die aerobe Entwicklung, während höhere Zonen sparsam für Schwellen- und Geschwindigkeitstraining genutzt werden. Diese Verteilung spiegelt die Trainingsmuster von Elite-Ausdauersportlern wider.</p>\n</div>\n<div class=\"example\">\n<h3>Beispiel 2: HIIT-Sitzung zum Fettabbau</h3>\n<p>Eine 30-jährige Frau mit einer maximalen Herzfrequenz von 190 Schlägen pro Minute entwirft eine hochintensive Intervalltrainingseinheit.</p>\n<p>Aufwärmen: Zone 1 (95–114 Schläge pro Minute) für 5 Minuten<br/>Arbeitsintervalle: Zone 5 (171–190 Schläge pro Minute) für 30 Sekunden × 8 Runden<br/>Erholung: Zone 2 (114–133 Schläge pro Minute) für 90 Sekunden zwischen den Intervallen<br/>Abkühlung: Zone 1 (95–114 Schläge pro Minute) für 5 Minuten</p>\n<p>Diese 28-minütige Sitzung maximiert den EPOC (übermäßiger Sauerstoffverbrauch nach dem Training) und sorgt für eine erhöhte Stoffwechselrate für Stunden nach dem Training. Der Wechsel zwischen Zone 5 und Zone 2 trainiert sowohl die anaerobe Kapazität als auch die Erholungseffizienz.</p>\n</div>\n</div>\n<div class=\"uses-section\">\n<h2>Allgemeine Verwendung</h2>\n<ul>\n<li>Strukturierung periodischer Trainingsprogramme, die im Laufe einer Saison systematisch verschiedene Energiesysteme entwickeln</li>\n<li>Sorgen Sie dafür, dass einfache Tage auch wirklich einfach bleiben, indem Sie Erholungsläufe in Zone 1–2 durchführen</li>\n<li>Entwerfen von Intervalltrainingsprotokollen mit präzisen Herzfrequenzzielen für Arbeit und Erholung</li>\n<li>Überwachung der Trainingsbelastung und Vermeidung von Übertraining durch zonenbasierte Zeitverteilungsanalyse</li>\n<li>Einstellen der geeigneten Intensität für Gruppenfitnesskurse, um unterschiedlichen Fitnessniveaus gerecht zu werden</li>\n<li>Verfolgen Sie Fitnessverbesserungen, da das gleiche Tempo mit der Zeit zu einer niedrigeren Herzfrequenz führt</li>\n</ul>\n</div>\n<div class=\"mistakes-section\">\n<h2>Häufige Fehler</h2>\n<ul>\n<li>Verbringen Sie zu viel Zeit in Zone 3 (der „Grauzone“), was zu schwierig für die Genesung, aber zu einfach für eine sinnvolle Anpassung ist</li>\n<li>Verwendung einer ungenauen Schätzung der maximalen Herzfrequenz, die alle Zonen falsch verschiebt, was zu Unter- oder Übertraining führt</li>\n<li>Dabei wird ignoriert, dass Zonen, die auf der maximalen Herzfrequenz basieren, sich von Zonen unterscheiden, die auf der Laktatschwelle basieren, die um 10–20 Schläge pro Minute unterschiedlich sein kann</li>\n<li>Zonen werden nicht angepasst, wenn sich die Fitness verbessert, was dazu führt, dass das Training immer weniger anspruchsvoll wird als beabsichtigt</li>\n</ul>\n</div>\n<div class=\"pro-tip\">\n<h2>Pro Tip</h2>\n<p>Befolgen Sie die 80/20-Regel: Verbringen Sie etwa 80 % Ihrer wöchentlichen Trainingszeit in den Zonen 1–2 und 20 % in den Zonen 4–5. Dieser polarisierte Ansatz, der durch Untersuchungen an Elite-Ausdauersportlern bestätigt wurde, führt zu überlegenen Fitnesszuwächsen im Vergleich zu Training mittlerer Intensität. Verwenden Sie aus Gründen der Genauigkeit einen Brustgurt-Herzfrequenzmesser, da optische Sensoren am Handgelenk bei schnellen Intensitätsänderungen um 5–15 Sekunden verzögert sein können, wodurch die Zonenverfolgung bei Intervallsitzungen weniger zuverlässig wird.</p>\n</div>\n<div class=\"faq-section\">\n<h2>Häufig gestellte Fragen</h2>\n<div class=\"faq-list\">\n<div class=\"faq-item\">\n<button aria-expanded=\"false\" class=\"faq-q\">Sollte ich für die Zonenberechnung die maximale Herzfrequenz oder die Laktatschwelle verwenden?</button>\n<div class=\"faq-a\">Auf der Laktatschwelle basierende Zonen sind für Leistungssportler genauer, da die Schwellenherzfrequenz unabhängig von der maximalen Herzfrequenz variiert. Maximale HF-Zonen sind jedoch einfacher zu berechnen und für Freizeitsportler ausreichend. Wenn Sie Zugang zu Laktatschwellentests haben, verwenden Sie diese Werte. Ansonsten bieten maximale HF-Zonen eine vernünftige Annäherung.</div>\n</div>\n<div class=\"faq-item\">\n<button aria-expanded=\"false\" class=\"faq-q\">In welcher Zone sollten Anfänger trainieren?</button>\n<div class=\"faq-a\">Anfänger sollten in den ersten 8–12 Wochen die meiste Zeit in Zone 2 (60–70 % maximale Herzfrequenz) verbringen. Dadurch wird die aerobe Kapazität gestärkt, das Herz-Kreislauf-System gestärkt und die Effizienz der Fettverbrennung gesteigert, ohne dass es zu übermäßiger Ermüdung oder Verletzungsgefahr kommt. Führen Sie nach und nach die Arbeit in Zone 3 ein, nachdem Sie eine aerobe Basis geschaffen haben.</div>\n</div>\n<div class=\"faq-item\">\n<button aria-expanded=\"false\" class=\"faq-q\">Wie lange sollte ich während der Pausen in Zone 5 bleiben?</button>\n<div class=\"faq-a\">Die Anstrengungen in Zone 5 sollten kurz sein: maximal 30 Sekunden bis maximal 2 Minuten pro Intervall, mit vollständiger Erholung zwischen den Anstrengungen. Zone 5 stellt eine nahezu maximale bis maximale Anstrengung dar und kann nicht über längere Zeiträume aufrechterhalten werden. Typische HIIT-Sitzungen umfassen 6–12 Zone-5-Intervalle mit gleichen oder längeren Erholungsphasen in Zone 1–2.</div>\n</div>\n<div class=\"faq-item\">\n<button aria-expanded=\"false\" class=\"faq-q\">Ändern sich die Herzfrequenzzonen mit dem Alter?</button>\n<div class=\"faq-a\">Ja. Da die maximale Herzfrequenz um etwa 1 Schlag pro Minute pro Jahr abnimmt, verschieben sich Ihre absoluten Zonengrenzen mit zunehmendem Alter nach unten. Berechnen Sie Ihre Zonen jährlich oder immer dann neu, wenn Sie eine konstante Änderung Ihrer maximalen Herzfrequenz bemerken. Die prozentualen Grenzen (50–60 %, 60–70 % usw.) bleiben jedoch unabhängig vom Alter gleich.</div>\n</div>\n</div>\n</div>\n<div class=\"related-calculators\">\n<h2>Verwandte Rechner</h2>\n<ul> <li><a href=\"/en/karvonen-heart-rate/\">Karvonen Heart Rate Calculator</a></li>\n<li><a href=\"/en/bmr-harris-benedict/\">BMR (Harris-Benedict) Calculator</a></li>\n<li><a href=\"/en/bmr-katch-mcardle/\">BMR (Katch-McArdle) Calculator</a></li>\n<li><a href=\"/en/mets-calculator/\">Weight Loss Calculator</a></li>\n<li><a href=\"/en/permutations-calculator/\">Heart Rate Zones Calculator</a></li>\n</ul>\n</div>\n</section>\n"
    },
    "it": {
      "name": "Zone di Frequenza Cardiaca",
      "description": "Calcola le 5 zone di allenamento cardiaco in base all'età.",
      "inputs": {
        "age": "Età"
      },
      "outputs": {
        "zone1": "Zona 1",
        "zone2": "Zona 2",
        "zone3": "Zona 3",
        "zone4": "Zona 4",
        "zone5": "Zona 5"
      },
      "seo_title": "Zone di Frequenza Cardiaca – Strumento Gratuito",
      "seo_description": "Calcola le 5 zone di allenamento cardiaco in base all'età. Calcolatore gratuito, preciso e istantaneo. Ottieni risultati istantanei con spiegazione passo.",
      "example_label": "Determinare zonas de frequenza cardíaca per persona de 30 anni",
      "range_hints": {
        "age": "Edad típica: 18-80 er"
      },
      "result_context": "Zona 1-2 è quema de grasa, Zona 3-4 è cardio, Zona 5 è anaeróbico massimo per intervalos.",
      "formula_display": "Zona 1: 50-60% FCmáx; Zona 2: 60-70%; Zona 3: 70-80%; Zona 4: 80-90%; Zona 5: 90-100%",
      "steps": [
        "El calculador aplica la formula automaticamente e muestra risultati"
      ],
      "mistakes": [
        "No verificare que age estén en unita correctas prima de calcolare",
        "Arrotondare valori intermedios prima del calcolo finale (pierde precisión)",
        "Applicare risultati senza considerare contexto individual o condiciones especiales"
      ],
      "long_content": "<section class=\"long-content\">\n<h1>Calcolatore delle zone di allenamento della frequenza cardiaca: allenati in modo più intelligente</h1>\n<p>Le zone di allenamento della frequenza cardiaca dividono la frequenza cardiaca massima in cinque intervalli di intensità distinti, ciascuno mirato a diversi adattamenti fisiologici e sistemi energetici. L'allenamento nella zona corretta ti garantisce di ricevere lo stimolo giusto per i tuoi obiettivi di fitness specifici, che si tratti di costruire una base aerobica, migliorare la resistenza o sviluppare prestazioni di punta.</p>\n<p class=\"see-also\">Potresti anche trovare<a href=\"/it/frequenza-cardiaca-karvonen/\">Karvonen Heart Rate Calculator</a>, <a href=\"/it/fcmax-salute/\">Max Heart Rate Health Calculator</a>, and <a href=\"/it/clearance-creatinina/\">Creatinine Clearance (Cockcroft-Gault)</a> useful.</p>\ncollegamenti-<div class=\"formula-section\">\n<h2>Formula delle zone di allenamento della frequenza cardiaca</h2>\n<p class=\"formula-display\">Zona 1: 50-60% FC massima  |  Zona 2: 60-70% FC massima  |  Zona 3: 70–80% FC massima<br/>Zona 4: 80–90% FC massima  |  Zona 5: 90–100% FC massima</p>\n<p>Per prima cosa stimare la frequenza cardiaca massima utilizzando 220 − età (o un valore misurato da un test da sforzo graduale). Quindi calcola ciascuna zona moltiplicando la tua FC massima per l'intervallo percentuale corrispondente. Per un 35enne con una frequenza cardiaca massima stimata di 185 bpm: Zona 1 = 93–111 bpm (riscaldamento/recupero), Zona 2 = 111–130 bpm (brucia grassi/base aerobica), Zona 3 = 130–148 bpm (resistenza aerobica), Zona 4 = 148–167 bpm (soglia del lattato), Zona 5 = 167–185 bpm (sforzo massimo/anaerobico).</p>\n</div>\n<div class=\"examples-section\">\n<h2>Esempi realizzati</h2>\n<div class=\"example\">\n<h3>Esempio 1: Piano di allenamento per la maratona</h3>\n<p>Un quarantenne che si prepara per una maratona ha una frequenza cardiaca massima di 180 bpm e desidera strutturare l'allenamento settimanale in più zone.</p>\n<p>Zona 2 (60–70%): 108–126 bpm — 3 corse lunghe a settimana<br/>Zona 3 (70–80%): 126–144 bpm — 1 corsa a tempo a settimana<br/>Zona 4 (80–90%): 144–162 bpm — 1 sessione a intervalli a settimana</p>\n<p>Questo approccio polarizzato trascorre l'80% del tempo di allenamento nella Zona 2 per lo sviluppo aerobico, mentre utilizza con parsimonia le zone più alte per il lavoro sulla soglia e sulla velocità. Questa distribuzione rispecchia i modelli di allenamento degli atleti di resistenza d’élite.</p>\n</div>\n<div class=\"example\">\n<h3>Esempio 2: sessione HIIT per dimagrire</h3>\n<p>Una donna di 30 anni con una frequenza cardiaca massima di 190 bpm progetta una sessione di allenamento a intervalli ad alta intensità.</p>\n<p>Riscaldamento: Zona 1 (95–114 bpm) per 5 minuti<br/>Intervalli di lavoro: Zona 5 (171–190 bpm) per 30 secondi × 8 round<br/>Recupero: Zona 2 (114–133 bpm) per 90 secondi tra gli intervalli<br/>Defaticamento: Zona 1 (95–114 bpm) per 5 minuti</p>\n<p>Questa sessione di 28 minuti massimizza l'EPOC (consumo eccessivo di ossigeno post-esercizio), creando un tasso metabolico elevato per ore dopo l'esercizio. L'alternanza tra Zona 5 e Zona 2 allena sia la capacità anaerobica che l'efficienza di recupero.</p>\n</div>\n</div>\n<div class=\"uses-section\">\n<h2>Usi comuni</h2>\n<ul>\n<li>Strutturare programmi di allenamento periodici che sviluppano sistematicamente diversi sistemi energetici nel corso di una stagione</li>\n<li>Garantire che i giorni facili rimangano davvero facili mantenendo le corse di recupero nella Zona 1–2</li>\n<li>Progettare protocolli di allenamento a intervalli con obiettivi precisi di frequenza cardiaca di lavoro e recupero</li>\n<li>Monitoraggio del carico di allenamento e prevenzione del sovrallenamento attraverso l'analisi della distribuzione temporale basata sulle zone</li>\n<li>Impostazione dell'intensità adeguata per le lezioni di fitness di gruppo per adattarsi a diversi livelli di forma fisica</li>\n<li>Il monitoraggio dei miglioramenti della forma fisica con lo stesso ritmo produce una frequenza cardiaca più bassa nel tempo</li>\n</ul>\n</div>\n<div class=\"mistakes-section\">\n<h2>Errori comuni</h2>\n<ul>\n<li>Trascorrere troppo tempo nella Zona 3 (la “zona grigia”), che è troppo difficile per il recupero ma troppo facile per un adattamento significativo</li>\n<li>Utilizzo di una stima imprecisa della frequenza cardiaca massima che sposta tutte le zone in modo errato, portando a sottoallenamento o sovrallenamento</li>\n<li>Ignorando che le zone basate sulla frequenza cardiaca massima differiscono dalle zone basate sulla soglia del lattato, che può essere diversa di 10-20 bpm</li>\n<li>Mancata regolazione delle zone man mano che la forma fisica migliora, facendo sì che l'allenamento diventi progressivamente meno impegnativo del previsto</li>\n</ul>\n</div>\n<div class=\"pro-tip\">\n<h2>Consiglio professionale</h2>\n<p>Segui la regola 80/20: trascorri circa l'80% del tuo tempo di allenamento settimanale nelle zone 1–2 e il 20% nelle zone 4–5. Questo approccio polarizzato, convalidato dalla ricerca sugli atleti di resistenza d’élite, produce guadagni di forma fisica superiori rispetto all’allenamento di intensità moderata. Utilizza un cardiofrequenzimetro a fascia toracica per maggiore precisione, poiché i sensori ottici sul polso possono ritardare di 5-15 secondi durante rapidi cambiamenti di intensità, rendendo il monitoraggio delle zone meno affidabile durante le sessioni a intervalli.</p>\n</div>\n<div class=\"faq-section\">\n<h2>Domande frequenti</h2>\n<div class=\"faq-list\">\n<div class=\"faq-item\">\n<button aria-expanded=\"false\" class=\"faq-q\">Devo utilizzare la FC massima o la soglia del lattato per i calcoli delle zone?</button>\n<div class=\"faq-a\">Le zone basate sulla soglia del lattato sono più precise per gli atleti professionisti, poiché la frequenza cardiaca di soglia varia indipendentemente dalla FC massima. Tuttavia, le zone FC massime sono più semplici da calcolare e sufficienti per gli utenti ricreativi. Se hai accesso al test della soglia del lattato, usa questi valori. Altrimenti, le zone FC massime forniscono un'approssimazione ragionevole.</p></div>\n</div>\n<div class=\"faq-item\">\n<button aria-expanded=\"false\" class=\"faq-q\">In quale zona dovrebbero allenarsi i principianti?</button>\n<div class=\"faq-a\">I principianti dovrebbero trascorrere la maggior parte del tempo nella Zona 2 (60–70% FC massima) per le prime 8–12 settimane. Ciò aumenta la capacità aerobica, rafforza il sistema cardiovascolare e sviluppa l’efficienza nel bruciare i grassi senza eccessivo affaticamento o rischio di lesioni. Introdurre gradualmente il lavoro della Zona 3 dopo aver stabilito una base aerobica.</p></div>\n</div>\n<div class=\"faq-item\">\n<button aria-expanded=\"false\" class=\"faq-q\">Quanto tempo dovrei rimanere nella Zona 5 durante gli intervalli?</button>\n<div class=\"faq-a\">Gli sforzi della Zona 5 dovrebbero essere brevi: da 30 secondi a 2 minuti al massimo per intervallo, con recupero completo tra uno sforzo e l'altro. La zona 5 rappresenta uno sforzo quasi massimo o massimo e non può essere sostenuta per lunghi periodi. Le sessioni HIIT tipiche includono 6-12 intervalli nella Zona 5 con periodi di recupero uguali o più lunghi nella Zona 1-2.</p></div>\n</div>\n<div class=\"faq-item\">\n<button aria-expanded=\"false\" class=\"faq-q\">Le zone di frequenza cardiaca cambiano con l'età?</button>\n<div class=\"faq-a\">SÌ. Poiché la frequenza cardiaca massima diminuisce di circa 1 bpm all'anno, i confini assoluti della zona si spostano verso il basso con l'età. Ricalcola le tue zone ogni anno o ogni volta che noti un cambiamento consistente nella tua FC massima. Tuttavia, i limiti percentuali (50–60%, 60–70%, ecc.) rimangono gli stessi indipendentemente dall’età.</p></div>\n</div>\n</div>\n</div>\n<div class=\"related-calculators\">\n<h2>Calcolatori correlati</h2>\n<ul> <li><a href=\"/it/frequenza-cardiaca-karvonen/\">Karvonen Heart Rate Calculator</a></li>\n<li><a href=\"/it/\">BMR (Harris-Benedict) Calculator</a></li>\n<li><a href=\"/it/\">BMR (Katch-McArdle) Calculator</a></li>\n<li><a href=\"/it/\">Weight Loss Calculator</a></li>\n<li><a href=\"/it/heart-rate-zones/\">Heart Rate Zones Calculator</a></li>\n</ul>\n</div>\n\n</section>\n"
    }
  }
}