{
  "id": "946",
  "slug": "kinetic-energy",
  "block": 15,
  "block_slug": "ciencia",
  "inputs": [
    {
      "id": "masa",
      "type": "number",
      "min": 0.001,
      "max": 999999,
      "step": 0.001,
      "default": 10,
      "unit": "kg",
      "unit_options": [
        "kg",
        "g",
        "lb"
      ],
      "unit_category": "mass"
    },
    {
      "id": "velocidad",
      "type": "number",
      "min": 0,
      "max": 999999,
      "step": 0.1,
      "default": 5,
      "unit": "m/s",
      "unit_options": [
        "m/s",
        "km/h",
        "ft/s"
      ],
      "unit_category": "speed"
    }
  ],
  "formula": "var m=parseFloat(inputs.masa)||0,v=parseFloat(inputs.velocidad)||0;if(!m||!v)return{error:true};var ke=+(0.5*m*v*v).toFixed(2);return{kinetic_energy:ke,joules:ke,calories:+(ke/4184).toFixed(4)};",
  "outputs": [
    {
      "id": "kinetic_energy",
      "unit": "J",
      "highlight": true
    },
    {
      "id": "joules",
      "unit": "J",
      "highlight": false
    },
    {
      "id": "calories",
      "unit": "cal",
      "highlight": false
    }
  ],
  "related": [
    "947",
    "948",
    "127",
    "703"
  ],
  "example_inputs": {
    "masa": 10,
    "velocidad": 5
  },
  "comparison_presets": [
    {
      "_label": "Escala laboratorio",
      "masa": 4.0,
      "velocidad": 2.0
    },
    {
      "_label": "Uso domestico",
      "masa": 7.0,
      "velocidad": 3.5
    },
    {
      "_label": "Aplicacion industrial",
      "masa": 10.0,
      "velocidad": 5.0
    },
    {
      "_label": "Ingenieria civil",
      "masa": 15.0,
      "velocidad": 7.5
    },
    {
      "_label": "Escala cientifica",
      "masa": 25.0,
      "velocidad": 12.5
    }
  ],
  "units": {
    "masa": "kg",
    "velocidad": "m/s"
  }
}